teleapi/__init__.py
teleapi/httpx_transport.py
teleapi/teleapi.py
teleapi/teleproxy.py
teleapi/teletransport.py
pure_teleapi-1.8.3.dist-info/LICENSE
pure_teleapi-1.8.3.dist-info/METADATA
pure_teleapi-1.8.3.dist-info/WHEEL
pure_teleapi-1.8.3.dist-info/RECORD
