Metadata-Version: 2.1
Name: pure-teleapi
Version: 1.8.3
Summary: Pure declarative Telegram Bot API and implementation with pydantic models and sync and async API Protocol.
Home-page: https://github.com/AntonOvsyannikov/pure-teleapi
License: MIT
Author: Anton Ovsyannikov
Author-email: anton.ovsyannikov@gmail.com
Requires-Python: >=3.7,<4.0
Classifier: License :: OSI Approved :: MIT License
Classifier: Programming Language :: Python :: 3
Classifier: Programming Language :: Python :: 3.7
Classifier: Programming Language :: Python :: 3.8
Classifier: Programming Language :: Python :: 3.9
Classifier: Programming Language :: Python :: 3.10
Classifier: Programming Language :: Python :: 3.11
Classifier: Programming Language :: Python :: 3.12
Provides-Extra: httpx
Requires-Dist: httpx ; extra == "httpx"
Requires-Dist: pydantic
Project-URL: Repository, https://github.com/AntonOvsyannikov/pure-teleapi
